jaxns/__init__.py
jaxns/plotting.py
jaxns/public.py
jaxns/utils.py
jaxns/warnings.py
jaxns/experimental/__init__.py
jaxns/experimental/evidence_maximisation.py
jaxns/experimental/global_optimisation.py
jaxns/experimental/public.py
jaxns/experimental/solvers/__init__.py
jaxns/experimental/solvers/ad_utils.py
jaxns/experimental/solvers/cg.py
jaxns/experimental/solvers/gauss_newton_cg.py
jaxns/experimental/solvers/test_cg.py
jaxns/experimental/solvers/tests/__init__.py
jaxns/experimental/solvers/tests/test_ad_utils.py
jaxns/experimental/solvers/tests/test_gauss_newton_cg.py
jaxns/experimental/tests/__init__.py
jaxns/experimental/tests/performance_tests.py
jaxns/experimental/tests/test_evidence_maximisation.py
jaxns/experimental/tests/test_global_optimisation.py
jaxns/framework/__init__.py
jaxns/framework/abc.py
jaxns/framework/bases.py
jaxns/framework/context.py
jaxns/framework/jaxify.py
jaxns/framework/model.py
jaxns/framework/ops.py
jaxns/framework/prior.py
jaxns/framework/special_priors.py
jaxns/framework/wrapped_tfp_distribution.py
jaxns/framework/tests/__init__.py
jaxns/framework/tests/test_context.py
jaxns/framework/tests/test_jaxify.py
jaxns/framework/tests/test_model.py
jaxns/framework/tests/test_prior.py
jaxns/internals/__init__.py
jaxns/internals/constraint_bijections.py
jaxns/internals/cumulative_ops.py
jaxns/internals/interp_utils.py
jaxns/internals/linalg.py
jaxns/internals/log_semiring.py
jaxns/internals/logging.py
jaxns/internals/maps.py
jaxns/internals/mixed_precision.py
jaxns/internals/namedtuple_utils.py
jaxns/internals/prefix_sum.py
jaxns/internals/pytree_utils.py
jaxns/internals/random.py
jaxns/internals/shapes.py
jaxns/internals/shrinkage_statistics.py
jaxns/internals/stats.py
jaxns/internals/tree_structure.py
jaxns/internals/types.py
jaxns/internals/tests/__init__.py
jaxns/internals/tests/test_constraint_bijections.py
jaxns/internals/tests/test_cumulative_ops.py
jaxns/internals/tests/test_interp_utils.py
jaxns/internals/tests/test_linalg.py
jaxns-2.6.9.dist-info/licenses/LICENSE
jaxns-2.6.9.dist-info/METADATA
jaxns-2.6.9.dist-info/WHEEL
jaxns-2.6.9.dist-info/top_level.txt
jaxns-2.6.9.dist-info/RECORD
