Metadata-Version: 2.4
Name: jaxns
Version: 2.6.9
Summary: Nested Sampling in JAX
Author-email: "Joshua G. Albert" <albert@strw.leidenuniv.nl>
License: Apache Software License 2.0
Project-URL: Homepage, https://github.com/joshuaalbert/jaxns
Keywords: bayesian-methods,scientific-computing,probabilistic-programming,nested-sampling,model-comparison,bayesian-computing,jax,scientific-machine-learning
Classifier: Programming Language :: Python :: 3
Classifier: License :: OSI Approved :: Apache Software License
Classifier: Operating System :: OS Independent
Requires-Python: >=3.9
License-File: LICENSE
Requires-Dist: jax>=0.6.0
Requires-Dist: jaxlib
Requires-Dist: matplotlib
Requires-Dist: numpy
Requires-Dist: scipy
Requires-Dist: tfp_nightly
Provides-Extra: examples
Requires-Dist: scikit-learn; extra == "examples"
Requires-Dist: optax; extra == "examples"
Provides-Extra: experimental
Provides-Extra: tests
Requires-Dist: scikit-learn; extra == "tests"
Requires-Dist: networkx; extra == "tests"
Requires-Dist: psutil; extra == "tests"
Requires-Dist: pytest; extra == "tests"
Requires-Dist: flake8; extra == "tests"
Dynamic: license-file
Dynamic: provides-extra
Dynamic: requires-dist
